<?xml version="1.0" encoding="UTF-8" ?>
<view x:extends="_gen/_ErpCrmCampaign.view.xml" x:schema="/nop/schema/xui/xview.xdef" xmlns:x="/nop/schema/xdsl.xdef">

    <grids>
                <grid id="list">
            <cols x:override="bounded-merge">
                <col id="id" mandatory="true" ui:number="true" sortable="true"/>
                <col id="code" mandatory="true" sortable="true"/>
                <col id="name" sortable="true"/>
                <col id="orgId" label="业务组织"/>
                <col id="campaignName" sortable="true"/>
                <col id="medium" sortable="true"/>
                <col id="source" sortable="true"/>
                <col id="startDate" sortable="true" align="center">
                    <gen-control>
                        <c:script><![CDATA[
                            return { type: 'date', format: 'YYYY-MM-DD' };
                        ]]></c:script>
                    </gen-control>
                </col>
                <col id="endDate" sortable="true" align="center">
                    <gen-control>
                        <c:script><![CDATA[
                            return { type: 'date', format: 'YYYY-MM-DD' };
                        ]]></c:script>
                    </gen-control>
                </col>
                <col id="budgetAmount" ui:number="true" sortable="true" align="right">
                    <gen-control>
                        <c:script><![CDATA[
                            return { type: 'number', kilometer: true, precision: 2 };
                        ]]></c:script>
                    </gen-control>
                </col>
                <col id="actualCost" ui:number="true" sortable="true" align="right">
                    <gen-control>
                        <c:script><![CDATA[
                            return { type: 'number', kilometer: true, precision: 2 };
                        ]]></c:script>
                    </gen-control>
                </col>
            </cols>
        </grid>
        <grid id="pick-list"/>
    </grids>

    <forms>
        <form id="view"/>
        <form id="edit"/>
        <form id="add"/>
    </forms>

    <pages>
        <crud name="main"/>
        <picker name="picker"/>
    </pages>
</view>