<?xml version="1.0" encoding="UTF-8" ?>
<view x:extends="_gen/_ErpMntVisit.view.xml" x:schema="/nop/schema/xui/xview.xdef" xmlns:x="/nop/schema/xdsl.xdef">

    <grids>
        <grid id="list">
            <cols x:override="bounded-merge">
                <col id="id" mandatory="true" ui:number="true" sortable="true"/>
                <col id="code" mandatory="true" sortable="true"/>
                <col id="orgId" label="组织"/>
                <col id="scheduleCode" label="维护计划"/>
                <col id="equipmentCode" label="设备"/>
                <col id="visitDate" mandatory="true" sortable="true"/>
                <col id="visitType" sortable="true"/>
                <col id="status" mandatory="true" sortable="true"/>
                <col id="startTime" sortable="true"/>
                <col id="endTime" sortable="true"/>
                <col id="totalMinutes" ui:number="true" sortable="true"/>
                <col id="result" sortable="true"/>
            </cols>
        </grid>
        <grid id="pick-list"/>
    </grids>

    <forms>
        <form id="view">
            <layout x:override="replace">
==========>baseInfo[基本信息]======
 code[访问编码] scheduleId[维护计划ID]
 equipmentId[设备ID] visitDate[访问日期]
 status[状态] visitType[维护类型]
 orgId[业务组织] businessDate[业务日期]
==========>execution[执行信息]======
 assignedTo[指派人] completedBy[完成人]
 completedAt[完成时间] startTime[开始时间]
 endTime[结束时间] totalMinutes[总分钟数]
 result[执行结果]
==========^audit[审计信息]=========
 remark[备注]
 createdBy[创建人] createTime[创建时间]
 updatedBy[修改人] updateTime[修改时间]
            </layout>
        </form>
        <form id="edit">
            <layout x:override="replace">
==========>baseInfo[基本信息]======
 code[访问编码] scheduleId[维护计划ID]
 equipmentId[设备ID] visitDate[访问日期]
 status[状态] visitType[维护类型]
 orgId[业务组织] businessDate[业务日期]
==========>execution[执行信息]======
 assignedTo[指派人] completedBy[完成人]
 completedAt[完成时间] startTime[开始时间]
 endTime[结束时间] totalMinutes[总分钟数]
 result[执行结果]
 remark[备注](2)
            </layout>
        </form>
        <form id="add"/>
        <form id="query" editMode="query" title="查询条件">
            <layout>
 code[访问编码] status[状态]
 equipmentId[设备ID] visitDate[访问日期]
            </layout>
            <cells>
                <cell id="code" filterOp="like"/>
                <cell id="visitDate" filterOp="date-between"/>
            </cells>
        </form>
    </forms>

    <pages>
        <crud name="main"/>
        <picker name="picker"/>
    </pages>
</view>