{
  "id": 0,
  "code": "",
  "orgId": 0,
  "subject": "",
  "description": "",
  "customerId": 0,
  "contactId": 0,
  "ticketTypeId": 0,
  "priority": "",
  "priority_label": "",
  "source": "",
  "source_label": "",
  "assignedToId": "",
  "slaPolicyId": 0,
  "deadlineDateTime": "2000-01-01 14:00:00",
  "isSlaCompleted": false,
  "startDateTime": "2000-01-01 14:00:00",
  "endDateTime": "2000-01-01 14:00:00",
  "duration": 0,
  "progress": 0,
  "status": "",
  "status_label": "",
  "docStatus": "",
  "docStatus_label": "",
  "approveStatus": "",
  "approveStatus_label": "",
  "remark": "",
  "catalogItemId": 0,
  "delVersion": 0,
  "version": 0,
  "createdBy": "",
  "createTime": "2000-01-01 14:00:00",
  "updatedBy": "",
  "updateTime": "2000-01-01 14:00:00",
  "approvedBy": "",
  "approvedAt": "2000-01-01 14:00:00",
  "businessDate": "2000-01-01",
  "customer": null,
  "contact": null,
  "ticketType": null,
  "slaPolicy": null,
  "org": null,
  "catalogItem": null,
  "actions": null,
  "orgName": "",
  "customerName": "",
  "contactName": "",
  "ticketTypeName": "",
  "slaPolicyName": "",
  "catalogItemName": ""
}