{
  "data": {
    "extData": null,
    "hasNext": null,
    "hasPrev": null,
    "limit": 10,
    "nextCursor": null,
    "offset": 0,
    "page": 1,
    "pageCount": 1,
    "prevCursor": null,
    "total": 1,
    "items": [
      {
        "id": "2",
        "asnId": 1,
        "lineNo": 1,
        "materialId": null,
        "supplierPartNo": null,
        "quantity": null,
        "shippedQty": null,
        "remark": null,
        "delVersion": 0,
        "version": 0,
        "createdBy": "autotest-ref",
        "createTime": "@var:ErpB2bAsnLine@updateTime",
        "updatedBy": "autotest-ref",
        "updateTime": "@var:ErpB2bAsnLine@updateTime",
        "asnName": "SMOKE-B2B",
        "materialName": null
      }
    ]
  },
  "status": 0
}